abac/__init__.py
abac/db/__init__.py
abac/db/gremlin.py
abac/db/umongo.py.deprecated
abac/exceptions.py
abac/web/__init__.py
abac/web/aiohttp.py
pyabac-0.0.3.dist-info/LICENSE.rst
pyabac-0.0.3.dist-info/WHEEL
pyabac-0.0.3.dist-info/METADATA
pyabac-0.0.3.dist-info/RECORD
